{
	"name": "Duckcash",
	"type": "dark",
	"colors": {
	  "activityBar.background": "#212121",
	  "activityBar.dropBackground": "#1a1a1a",
	  "activityBar.border": "#1f242b",
	  "activityBar.foreground": "#cecece",
	  "activityBarBadge.background": "#404754",
	  "activityBarBadge.foreground": "#212121",
	  "badge.background": "#363636",
	  "badge.foreground": "#212121",
	  "button.background": "#404754",
	  "diffEditor.insertedTextBackground": "#00809B33",
	  "editor.findMatchHighlightBackground": "#314365",
	  "editor.selectionHighlightBackground": "#ffffff10",
	  "editor.wordHighlightBackground": "#484e5b",
	  "editor.wordHighlightStrongBackground": "#abb2bf26",
	  "tree.indentGuidesStroke": "#21262D",
	  "editorError.foreground": "#E15A60",
	  "editorIndentGuide.activeBackground": "#232830",
	  "editorIndentGuide.background": "#232830",
	  "editorMarkerNavigation.background": "#1f242b",
	  "editorRuler.foreground": "#abb2bf26",
	  "editorSuggestWidget.selectedBackground": "#2c313a",
	  "editorWhitespace.foreground": "#3B4048",
	  "extensionButton.prominentBackground": "#1F242B",
	  "extensionButton.prominentHoverBackground": "#282D38",
	  "gitDecoration.addedResourceForeground": "#95E5A6",
	  "gitDecoration.conflictingResourceForeground": "#FFA5C3",
	  "gitDecoration.deletedResourceForeground": "#FFA5C3",
	  "gitDecoration.ignoredResourceForeground": "#64727f",
	  "gitDecoration.modifiedResourceForeground": "#8CD8D8",
	  "gitDecoration.untrackedResourceForeground": "#95E5A6",
	  "list.activeSelectionForeground": "#dfe1e8",
	  "list.focusBackground": "#232830",
	  "list.highlightForeground": "#C5C5C5",
	  "list.hoverForeground": "#c0c5cd",
	  "list.inactiveFocusBackground": "#23283050",
	  "peekViewEditor.matchHighlightBackground": "#29244b",
	  "statusBar.debuggingBackground": "#7e0097",
	  "statusBar.debuggingBorder": "#66017a",
	  "statusBarItem.hoverBackground": "#2c313a",
	  "widget.shadow": "#1F242B",
	  "button.foreground": "#cecece",
		"debugExceptionWidget.border": "#212121",
		"debugToolBar.background": "#1a1a1a",
		"dropdown.background": "#1a1a1a",
		"dropdown.border": "#1a1a1a",
		"dropdown.foreground": "#cecece",
		"editor.background": "#262626",
		"editor.foreground": "#cecece",
		"editor.hoverHighlightBackground": "#1a1a1a",
		"editor.lineHighlightBackground": "#363636",
		"editor.lineHighlightBorder": "#00000000",
		"editor.selectionBackground": "#363636",
		"editorBracketMatch.background": "#212121",
		"editorCursor.background": "#363636",
		"editorCursor.foreground": "#cecece",
		"editorGroup.border": "#1a1a1a",
		"editorGroup.dropBackground": "#1a1a1a",
		"editorGroupHeader.noTabsBackground": "#212121",
		"editorGroupHeader.tabsBackground": "#212121",
		"editorGroupHeader.tabsBorder": "#1a1a1a",
		"editorGutter.background": "#262626",
		"editorHoverWidget.background": "#1a1a1a",
		"editorHoverWidget.border": "#1a1a1a",
		"editorLineNumber.activeForeground": "#cecece",
		"editorLineNumber.foreground": "#363636",
		"editorOverviewRuler.border": "#1a1a1a",
		"editorOverviewRuler.currentContentForeground": "#1a1a1a",
		"editorOverviewRuler.incomingContentForeground": "#1a1a1a",
		"editorSuggestWidget.background": "#212121",
		"editorSuggestWidget.border": "#1a1a1a",
		"editorSuggestWidget.foreground": "#cecece",
		"editorWidget.background": "#212121",
		"extensionButton.prominentForeground": "#cecece",
		"focusBorder": "#1a1a1a",
		"foreground": "#cecece",
		"input.background": "#1a1a1a",
		"input.border": "#1a1a1a",
		"input.foreground": "#cecece",
		"input.placeholderForeground": "#cecece",
		"list.activeSelectionBackground": "#363636",
		"list.focusForeground": "#cecece",
		"list.hoverBackground": "#1a1a1a",
		"list.inactiveSelectionBackground": "#363636",
		"list.inactiveSelectionForeground": "#cecece",
		"merge.border": "#1a1a1a",
		"panel.background": "#212121",
		"panel.border": "#1a1a1a",
		"panelTitle.inactiveForeground": "#cecece",
		"peekViewEditor.background": "#212121",
		"peekViewEditorGutter.background": "#212121",
		"peekViewResult.background": "#212121",
		"peekViewResult.lineForeground": "#cecece",
		"peekViewResult.selectionForeground": "#cecece",
		"peekViewTitle.background": "#1a1a1a",
		"peekViewTitleDescription.foreground": "#cecece",
		"pickerGroup.border": "#1a1a1a",
		"pickerGroup.foreground": "#cecece",
		"scrollbar.shadow": "#262626",
		"scrollbarSlider.activeBackground": "#726c6b99",
		"scrollbarSlider.background": "#726c6b66",
		"scrollbarSlider.hoverBackground": "#726c6b99",
		"sideBar.background": "#212121",
		"sideBar.border": "#1a1a1a",
		"sideBar.dropBackground": "#363636",
		"sideBar.foreground": "#cecece",
		"sideBarSectionHeader.background": "#1a1a1a",
		"sideBarSectionHeader.foreground": "#cecece",
		"sideBarTitle.foreground": "#cecece",
		"statusBar.background": "#1a1a1a",
		"statusBar.border": "#1a1a1a",
		"statusBar.debuggingForeground": "#cecece",
		"statusBar.foreground": "#cecece",
		"statusBar.noFolderBackground": "#1a1a1a",
		"statusBar.noFolderForeground": "#cecece",
		"statusBarItem.prominentBackground": "#1a1a1a",
		"tab.activeBackground": "#262626",
		"tab.activeBorder": "#262626",
		"tab.activeBorderTop": "#1a1a1a",
		"tab.activeForeground": "#cecece",
		"tab.border": "#1a1a1a",
		"tab.hoverBackground": "#212121",
		"tab.inactiveBackground": "#212121",
		"tab.inactiveForeground": "#cecece",
		"tab.unfocusedActiveForeground": "#cecece",
		"tab.unfocusedHoverBackground": "#1a1a1a",
		"tab.unfocusedInactiveForeground": "#cecece",
		"titleBar.activeBackground": "#212121",
		"titleBar.activeForeground": "#cecece",
		"titleBar.border": "#212121",
		"titleBar.inactiveBackground": "#212121",
		"titleBar.inactiveForeground": "#cecece",
		"walkThrough.embeddedEditorBackground": "#212121",
		"panelTitle.activeBorder": "#fff",
		"panelTitle.activeForeground": "#fff",
		"terminal.foreground": "#fff",
		"terminal.ansiBlack": "#fff",
		"terminal.ansiRed": "#f7899c",
		"terminal.ansiGreen": "#9bfba3",
		"terminal.ansiYellow": "#e1c342",
		"terminal.ansiBlue": "#39b1b3",
		"terminal.ansiMagenta": "#b200b3",
		"terminal.ansiCyan": "#00a6b3",
		"terminal.ansiWhite": "#c0bfbf",
		"terminal.ansiBrightBlack": "#c9c9c9",
		"terminal.ansiBrightRed": "#f8a3b3",
		"terminal.ansiBrightGreen": "#75fdc0",
		"terminal.ansiBrightYellow": "#f9ea8c",
		"terminal.ansiBrightBlue": "#43ccca",
		"terminal.ansiBrightMagenta": "#e601e5",
		"terminal.ansiBrightCyan": "#31f4f4",
		"terminal.ansiBrightWhite": "#e5e5e5",
		"terminal.selectionBackground": "#31f4f4",
		"terminalCursor.background": "#31f4f4",
		"terminalCursor.foreground": "#31f4f4"
	},
	"tokenColors": [
	  {
		"name": "Comments",
		"scope": "comment, punctuation.definition.comment",
		"settings": {
		  "foreground": "#c0c5cd50",
		  "fontStyle": "italic"
		}
	  },
	  {
		"name": "Flow Typedef",
		"scope": "meta.type.flowtype variable.other.flowtype, variable.other.property, variable.other.object, variable.other.readwrite, meta.template.expression, entity.name.type.module, punctuation.definition.entity, variable.parameter",
		"settings": {
		  "foreground": "#d4d4d4"
		}
	  },
	  {
		"name": "this, super",
		"scope": "variable.language.this, variable.language.super",
		"settings": {
		  "foreground": "#d4d4d4"
		}
	  },
	  {
		"name": "scss tag ref",
		"scope": "entity.name.tag.reference, entity.name.tag.css, entity.name.tag.scss",
		"settings": {
		  "foreground": "#FFA5C3"
		}
	  },
	  {
		"name": "Keyword",
		"scope": "keyword, storage.type, storage.type.function, variable.other.flowtype, storage.type.extends, storage.type.function, storage.type.class, keyword.operator.module",
		"settings": {
		  "foreground": "#7f7f7f"
		}
	  },
	  {
		"name": "Types, Tags",
		"scope": "entity.name.type",
		"settings": {
		  "foreground": "#8CD8D8",
		  "fontStyle": "underline"
		}
	  },
	  {
		"name": "Module",
		"scope": "entity.name.type.module",
		"settings": {
		  "fontStyle": ""
		}
	  },
	  {
		"name": "Storage",
		"scope": "storage.modifier",
		"settings": {
		  "foreground": "#7f7f7f"
		}
	  },
	  {
		"name": "Tags",
		"scope": "entity.name.tag",
		"settings": {
		  "foreground": "#7f7f7f"
		}
	  },
	  {
		"name": "Decorators",
		"scope": "meta.decorator, meta.decorator.tsx variable.other.readwrite.tsx, meta.decorator.tsx variable.other.object.tsx, meta.decorator.tsx variable.other.property.tsx, meta.decorator.jsx variable.other.readwrite.jsx, meta.decorator.jsx variable.other.object.jsx, meta.decorator.jsx variable.other.property.jsx",
		"settings": {
		  "foreground": "#7f7f7f"
		}
	  },
	  {
		"name": "Components",
		"scope": "support.class.component",
		"settings": {
		  "foreground": "#FFDFA5"
		}
	  },
	  {
		"name": "Function Call",
		"scope": "variable.function, source meta.function-call entity.name.function, meta.class meta.group.braces.curly meta.function-call variable.function, meta.class meta.field.declaration meta.function-call entity.name.function, variable.function.constructor, meta.block meta.var.expr meta.function-call entity.name.function, support.function.console, meta.function-call support.function, meta.property.class variable.other.class, punctuation.definition.entity.css",
		"settings": {
		  "foreground": "#FFDFA5"
		}
	  },
	  {
		"name": "Function/Class Name",
		"scope": "entity.name.function, meta.class entity.name.class, meta.class entity.name.type.class, meta.class meta.function-call variable.function, source keyword.control.loop, storage.type.function.arrow, keyword.other.important",
		"settings": {
		  "foreground": "#FFA5C3",
		  "fontStyle": ""
		}
	  },
	  {
		"name": "Control Flow",
		"scope": "keyword.control.flow",
		"settings": {
		  "foreground": "#FFA5C3"
		}
	  },
	  {
		"name": "Primitive types",
		"scope": "support.type.primitive",
		"settings": {
		  "foreground": "#8CD8D8",
		  "fontStyle": "italic"
		}
	  },
	  {
		"name": "Property json",
		"scope": "support.type.property-name",
		"settings": {
		  "foreground": "#d4d4d4"
		}
	  },
	  {
		"name": "Loops control",
		"scope": "keyword.control.trycatch, source meta.group.braces.curly keyword.control.loop, keyword.control.switch",
		"settings": {
		  "foreground": "#7f7f7f"
		}
	  },
	  {
		"name": "Punctuation terminator",
		"scope": "punctuation.terminator, punctuation.definition, punctuation.support, punctuation.separator.dictionary, punctuation.separator.array, meta.brace.round, punctuation.section.embedded, punctuation.accessor, meta.delimiter.comma, keyword.operator.ternary, punctuation.section.property-list, punctuation.section.function, punctuation.separator.comma, meta.function-call.without-arguments, constant.character.entity, entity.other.attribute-name.pseudo-class, meta.brace.curly, meta.brace.square, punctuation.separator.parameter, punctuation.operation.graphql",
		"settings": {
		  "foreground": "#7f7f7f"
		}
	  },
	  {
		"name": "Embedded exp - Substitution",
		"scope": "keyword.other.substitution, punctuation.definition.interpolation, punctuation.definition.template-expression",
		"settings": {
		  "foreground": "#7f7f7f"
		}
	  },
	  {
		"name": "Type annotation, key-value separator",
		"scope": "punctuation.separator.key-value, keyword.operator.type",
		"settings": {
		  "foreground": "#7f7f7f"
		}
	  },
	  {
		"name": "Optional",
		"scope": "keyword.operator.optional",
		"settings": {
		  "foreground": "#FFDFA5"
		}
	  },
	  {
		"name": "Assignment",
		"scope": "keyword.operator.assignment",
		"settings": {
		  "foreground": "#FFDFA5"
		}
	  },
	  {
		"name": "Logic",
		"scope": "keyword.operator.logical",
		"settings": {
		  "foreground": "#FFDFA5"
		}
	  },
	  {
		"name": "Comparison",
		"scope": "keyword.operator.comparison, keyword.operator.relational",
		"settings": {
		  "foreground": "#FFA5C3"
		}
	  },
	  {
		"name": "String",
		"scope": "string.quoted, string.interpolated, support.constant.property-value, keyword.other.unit, string.template, punctuation.definition.string",
		"settings": {
		  "foreground": "#95E5A6"
		}
	  },
	  {
		"name": "Literal",
		"scope": "constant.language, constant.numeric, support.constant, constant.character, constant.other.color, constant.other.symbol, constant.other.key",
		"settings": {
		  "foreground": "#8CD8D8"
		}
	  },
	  {
		"name": "Inserted",
		"scope": "markup.inserted",
		"settings": {
		  "foreground": "#99C794"
		}
	  },
	  {
		"name": "Deleted",
		"scope": "markup.deleted",
		"settings": {
		  "foreground": "#E15A60"
		}
	  },
	  {
		"name": "Changed",
		"scope": "markup.changed",
		"settings": {
		  "foreground": "#BB80B3"
		}
	  },
	  {
		"name": "URL",
		"scope": "*url*, *link*, *uri*",
		"settings": {
		  "fontStyle": "underline"
		}
	  },
	  {
		"name": "Search Results Nums",
		"scope": "constant.numeric.line-number.find-in-files - match",
		"settings": {
		  "foreground": "#AB7967"
		}
	  },
	  {
		"name": "Search Results Lines",
		"scope": "entity.name.filename.find-in-files",
		"settings": {
		  "foreground": "#99C794"
		}
	  },
	  {
		"scope": "token.info-token",
		"settings": {
		  "foreground": "#95E5A6"
		}
	  },
	  {
		"scope": "token.warn-token",
		"settings": {
		  "foreground": "#FFDFA5"
		}
	  },
	  {
		"scope": "token.error-token",
		"settings": {
		  "foreground": "#FFA5C3"
		}
	  },
	  {
		"scope": "token.debug-token",
		"settings": {
		  "foreground": "#8CD8D8"
		}
	  },
	  {
		"scope": "source entity.other.attribute-name",
		"settings": {
		  "foreground": "#FFDFA5",
		  "fontStyle": "italic"
		}
	  },
	  {
		"scope": "source meta.tag.attributes entity.other.attribute-name, meta.jsx.js entity.other.attribute-name.jsx",
		"settings": {
		  "foreground": "#d4d4d4",
		  "fontStyle": "italic"
		}
	  },
	  {
		"scope": "text.html.basic entity.other.attribute-name.html",
		"settings": {
		  "fontStyle": "italic"
		}
	  }
	]
  }